{
    "documents": [{
            "transactionId": "f082acfe-96df-4f1d-8ca0-0a5955e332db",
            "companyId": "9408235322",
            "partnerId": "7983038202",
            "nameCompany": "Productos Noel",
            "documentType": "ORDEN",
            "documentId": "123012",
            "country": "CO",
            "fileNameInput": "ftp-dacg-test.s3.amazonaws.com/documeprueba.txt",
            "fileNameOutput": "web-p2p-documents.s3.amazonaws.com/documeprueba.txt",
            "status": "PROCESADO",
            "documentDate": "2020-05-16T18:55:06.809068",
            "documentDelivery": "2020-05-17T20:55:06.809068",
            "message": ""
        },
        {
            "transactionId": "sd4d243d-96df-4f1d-8ca0-0a5955e332db",
            "companyId": "9408235322",
            "partnerId": "7983038202",
            "nameCompany": "Productos Noel",
            "documentType": "ORDEN",
            "documentId": "123012",
            "country": "CO",
            "fileNameInput": "ftp-dacg-test.s3.amazonaws.com/documeprueba.txt",
            "fileNameOutput": "web-p2p-documents.s3.amazonaws.com/documeprueba.txt",
            "status": "PROCESADO",
            "documentDate": "2020-05-16T18:55:06.809068",
            "documentDelivery": "2020-05-17T20:55:06.809068",
            "message": ""
        },
        {
            "transactionId": "sd4d243d-96df-4f1d-8ca0-0a5955e332db",
            "companyId": "9408235322",
            "partnerId": "7983038202",
            "nameCompany": "Productos Noel",
            "documentType": "ORDEN",
            "documentId": "123012",
            "country": "CO",
            "fileNameInput": "ftp-dacg-test.s3.amazonaws.com/documeprueba.txt",
            "fileNameOutput": "web-p2p-documents.s3.amazonaws.com/documeprueba.txt",
            "status": "PROCESADO",
            "documentDate": "2020-05-16T18:55:06.809068",
            "documentDelivery": "2020-05-17T20:55:06.809068",
            "message": ""
        },
        {
            "transactionId": "sd4d243d-96df-4f1d-8ca0-0a5955e332db",
            "companyId": "9408235322",
            "partnerId": "7983038202",
            "nameCompany": "Productos Noel",
            "documentType": "ORDEN",
            "documentId": "123012",
            "country": "CO",
            "fileNameInput": "ftp-dacg-test.s3.amazonaws.com/documeprueba.txt",
            "fileNameOutput": "web-p2p-documents.s3.amazonaws.com/documeprueba.txt",
            "status": "PROCESADO",
            "documentDate": "2020-05-16T18:55:06.809068",
            "documentDelivery": "2020-05-17T20:55:06.809068",
            "message": ""
        },
        {
            "transactionId": "sd4d243d-96df-4f1d-8ca0-0a5955e332db",
            "companyId": "9408235322",
            "partnerId": "7983038202",
            "nameCompany": "Productos Noel",
            "documentType": "ORDEN",
            "documentId": "123012",
            "country": "CO",
            "fileNameInput": "ftp-dacg-test.s3.amazonaws.com/documeprueba.txt",
            "fileNameOutput": "web-p2p-documents.s3.amazonaws.com/documeprueba.txt",
            "status": "PROCESADO",
            "documentDate": "2020-05-16T18:55:06.809068",
            "documentDelivery": "2020-05-17T20:55:06.809068",
            "message": ""
        },
        {
            "transactionId": "sd4d243d-96df-4f1d-8ca0-0a5955e332db",
            "companyId": "9408235322",
            "partnerId": "7983038202",
            "nameCompany": "Productos Noel",
            "documentType": "ORDEN",
            "documentId": "123012",
            "country": "CO",
            "fileNameInput": "ftp-dacg-test.s3.amazonaws.com/documeprueba.txt",
            "fileNameOutput": "web-p2p-documents.s3.amazonaws.com/documeprueba.txt",
            "status": "PROCESADO",
            "documentDate": "2020-05-16T18:55:06.809068",
            "documentDelivery": "2020-05-17T20:55:06.809068",
            "message": ""
        },
        {
            "transactionId": "sd4d243d-96df-4f1d-8ca0-0a5955e332db",
            "companyId": "9408235322",
            "partnerId": "7983038202",
            "nameCompany": "Productos Noel",
            "documentType": "ORDEN",
            "documentId": "123012",
            "country": "CO",
            "fileNameInput": "ftp-dacg-test.s3.amazonaws.com/documeprueba.txt",
            "fileNameOutput": "web-p2p-documents.s3.amazonaws.com/documeprueba.txt",
            "status": "PROCESADO",
            "documentDate": "2020-05-16T18:55:06.809068",
            "documentDelivery": "2020-05-17T20:55:06.809068",
            "message": ""
        }
    ]
}